Workbook

Sheet Trades
A1: 2026-06-23 | B1: Date Opened | C1: Ticker | D1: Direction | E1: Setup | F1: Entry Price | G1: Initial Stop | H1: Adjusted Stop (After 1R) | I1: Position Size (shares) | J1: Initial Risk $ | K1: Planned R Target | L1: Planned Profit Target | M1: Status | N1: Realized P&L | O1: Realized R | P1: Expected 1R | Q1: Expected 1.5R | R1: Expected 2R | S1: Expected 2.5R | T1: Expected 3R
A2: ="T-"& TEXT(ROW()-1,"000") -> T-001 | B2: 46072 | C2: ONDS | D2: Long | E2: CT Reversal | F2: 11.11 | G2: 9.81 | H2: =Tabla1[[#This Row],[Entry Price]]-(Tabla1[[#This Row],[Entry Price]]-Tabla1[[#This Row],[Initial Stop]])/2 -> 10.46 | I2: 18 | J2: =IF(D2="Long",(F2-G2)*I2,(G2-F2)*0) -> 23.4 | K2: 2 | L2: =J2*K2 -> 46.8 | M2: Closed | N2: =SUMIF(Executions!B:B,A2,Executions!H:H) -> -23.4 | O2: =N2/J2 -> -1 | P2: =Tabla1[[#This Row],[Initial Risk $]]/Tabla1[[#This Row],[Position Size (shares)]]+Tabla1[[#This Row],[Entry Price]] -> 12.41 | Q2: =Tabla1[[#This Row],[Initial Risk $]]/Tabla1[[#This Row],[Position Size (shares)]]*1.5+Tabla1[[#This Row],[Entry Price]] -> 13.06 | R2: =Tabla1[[#This Row],[Initial Risk $]]/Tabla1[[#This Row],[Position Size (shares)]]*2+Tabla1[[#This Row],[Entry Price]] -> 13.71 | S2: =Tabla1[[#This Row],[Initial Risk $]]/Tabla1[[#This Row],[Position Size (shares)]]*2.5+Tabla1[[#This Row],[Entry Price]] -> 14.36 | T2: =Tabla1[[#This Row],[Initial Risk $]]/Tabla1[[#This Row],[Position Size (shares)]]*3+Tabla1[[#This Row],[Entry Price]] -> 15.01
A3: ="T-"& TEXT(ROW()-1,"000") -> T-002 | B3: 46077 | C3: DNN | D3: Long | E3: Trend Continuation | F3: 4.18 | G3: 3.82 | H3: =Tabla1[[#This Row],[Entry Price]]-(Tabla1[[#This Row],[Entry Price]]-Tabla1[[#This Row],[Initial Stop]])/2 -> 4 | I3: 61 | J3: =IF(D3="Long",(F3-G3)*I3,(G3-F3)*0) -> 21.96 | K3: 2 | L3: =J3*K3 -> 43.92 | M3: Closed | N3: =SUMIF(Executions!B:B,A3,Executions!H:H) -> 6.71 | O3: =N3/J3 -> 0.30555556 | P3: =Tabla1[[#This Row],[Initial Risk $]]/Tabla1[[#This Row],[Position Size (shares)]]+Tabla1[[#This Row],[Entry Price]] -> 4.54 | Q3: =Tabla1[[#This Row],[Initial Risk $]]/Tabla1[[#This Row],[Position Size (shares)]]*1.5+Tabla1[[#This Row],[Entry Price]] -> 4.72 | R3: =Tabla1[[#This Row],[Initial Risk $]]/Tabla1[[#This Row],[Position Size (shares)]]*2+Tabla1[[#This Row],[Entry Price]] -> 4.9 | S3: =Tabla1[[#This Row],[Initial Risk $]]/Tabla1[[#This Row],[Position Size (shares)]]*2.5+Tabla1[[#This Row],[Entry Price]] -> 5.08 | T3: =Tabla1[[#This Row],[Initial Risk $]]/Tabla1[[#This Row],[Position Size (shares)]]*3+Tabla1[[#This Row],[Entry Price]] -> 5.26
A4: ="T-"& TEXT(ROW()-1,"000") -> T-003 | B4: 46077 | C4: TMDX | D4: Long | E4: Breakout | F4: 136.94 | G4: 127.28 | H4: =Tabla1[[#This Row],[Entry Price]]-(Tabla1[[#This Row],[Entry Price]]-Tabla1[[#This Row],[Initial Stop]])/2 -> 132.11 | I4: 3 | J4: =IF(D4="Long",(F4-G4)*I4,(G4-F4)*0) -> 28.98 | K4: 2 | L4: =J4*K4 -> 57.96 | M4: Closed | N4: =SUMIF(Executions!B:B,A4,Executions!H:H) -> -35.01 | O4: =N4/J4 -> -1.2080745 | P4: =Tabla1[[#This Row],[Initial Risk $]]/Tabla1[[#This Row],[Position Size (shares)]]+Tabla1[[#This Row],[Entry Price]] -> 146.6 | Q4: =Tabla1[[#This Row],[Initial Risk $]]/Tabla1[[#This Row],[Position Size (shares)]]*1.5+Tabla1[[#This Row],[Entry Price]] -> 151.43 | R4: =Tabla1[[#This Row],[Initial Risk $]]/Tabla1[[#This Row],[Position Size (shares)]]*2+Tabla1[[#This Row],[Entry Price]] -> 156.26 | S4: =Tabla1[[#This Row],[Initial Risk $]]/Tabla1[[#This Row],[Position Size (shares)]]*2.5+Tabla1[[#This Row],[Entry Price]] -> 161.09 | T4: =Tabla1[[#This Row],[Initial Risk $]]/Tabla1[[#This Row],[Position Size (shares)]]*3+Tabla1[[#This Row],[Entry Price]] -> 165.92
A5: ="T-"& TEXT(ROW()-1,"000") -> T-004 | B5: 46070 | C5: NG | D5: Long | E5: Breakout | F5: 10.37 | G5: 9.45 | H5: =Tabla1[[#This Row],[Entry Price]]-(Tabla1[[#This Row],[Entry Price]]-Tabla1[[#This Row],[Initial Stop]])/2 -> 9.91 | I5: 36 | J5: =IF(D5="Long",(F5-G5)*I5,(G5-F5)*0) -> 33.12 | K5: 1.5 | L5: =J5*K5 -> 49.68 | M5: Closed | N5: =SUMIF(Executions!B:B,A5,Executions!H:H) -> 59.31 | O5: =N5/J5 -> 1.7907609 | P5: =Tabla1[[#This Row],[Initial Risk $]]/Tabla1[[#This Row],[Position Size (shares)]]+Tabla1[[#This Row],[Entry Price]] -> 11.29 | Q5: =Tabla1[[#This Row],[Initial Risk $]]/Tabla1[[#This Row],[Position Size (shares)]]*1.5+Tabla1[[#This Row],[Entry Price]] -> 11.75 | R5: =Tabla1[[#This Row],[Initial Risk $]]/Tabla1[[#This Row],[Position Size (shares)]]*2+Tabla1[[#This Row],[Entry Price]] -> 12.21 | S5: =Tabla1[[#This Row],[Initial Risk $]]/Tabla1[[#This Row],[Position Size (shares)]]*2.5+Tabla1[[#This Row],[Entry Price]] -> 12.67 | T5: =Tabla1[[#This Row],[Initial Risk $]]/Tabla1[[#This Row],[Position Size (shares)]]*3+Tabla1[[#This Row],[Entry Price]] -> 13.13
A6: ="T-"& TEXT(ROW()-1,"000") -> T-005 | B6: 46078 | C6: ATEC | D6: Long | E6: CT Reversal | F6: 13.39 | G6: 12.39 | H6: =Tabla1[[#This Row],[Entry Price]]-(Tabla1[[#This Row],[Entry Price]]-Tabla1[[#This Row],[Initial Stop]])/2 -> 12.89 | I6: 19 | J6: =IF(D6="Long",(F6-G6)*I6,(G6-F6)*0) -> 19 | K6: 2 | L6: =J6*K6 -> 38 | M6: Closed | N6: =SUMIF(Executions!B:B,A6,Executions!H:H) -> -10.602 | O6: =N6/J6 -> -0.558 | P6: =Tabla1[[#This Row],[Initial Risk $]]/Tabla1[[#This Row],[Position Size (shares)]]+Tabla1[[#This Row],[Entry Price]] -> 14.39 | Q6: =Tabla1[[#This Row],[Initial Risk $]]/Tabla1[[#This Row],[Position Size (shares)]]*1.5+Tabla1[[#This Row],[Entry Price]] -> 14.89 | R6: =Tabla1[[#This Row],[Initial Risk $]]/Tabla1[[#This Row],[Position Size (shares)]]*2+Tabla1[[#This Row],[Entry Price]] -> 15.39 | S6: =Tabla1[[#This Row],[Initial Risk $]]/Tabla1[[#This Row],[Position Size (shares)]]*2.5+Tabla1[[#This Row],[Entry Price]] -> 15.89 | T6: =Tabla1[[#This Row],[Initial Risk $]]/Tabla1[[#This Row],[Position Size (shares)]]*3+Tabla1[[#This Row],[Entry Price]] -> 16.39
A7: ="T-"& TEXT(ROW()-1,"000") -> T-006 | B7: 46079 | C7: ROKU | D7: Long | E7: Reversal | F7: 92.49 | G7: 87.03 | H7: =Tabla1[[#This Row],[Entry Price]]-(Tabla1[[#This Row],[Entry Price]]-Tabla1[[#This Row],[Initial Stop]])/2 -> 89.76 | I7: 3 | J7: =IF(D7="Long",(F7-G7)*I7,(G7-F7)*0) -> 16.38 | K7: 2 | L7: =J7*K7 -> 32.76 | M7: Closed | N7: =SUMIF(Executions!B:B,A7,Executions!H:H) -> -14.31 | O7: =N7/J7 -> -0.87362637 | P7: =Tabla1[[#This Row],[Initial Risk $]]/Tabla1[[#This Row],[Position Size (shares)]]+Tabla1[[#This Row],[Entry Price]] -> 97.95 | Q7: =Tabla1[[#This Row],[Initial Risk $]]/Tabla1[[#This Row],[Position Size (shares)]]*1.5+Tabla1[[#This Row],[Entry Price]] -> 100.68 | R7: =Tabla1[[#This Row],[Initial Risk $]]/Tabla1[[#This Row],[Position Size (shares)]]*2+Tabla1[[#This Row],[Entry Price]] -> 103.41 | S7: =Tabla1[[#This Row],[Initial Risk $]]/Tabla1[[#This Row],[Position Size (shares)]]*2.5+Tabla1[[#This Row],[Entry Price]] -> 106.14 | T7: =Tabla1[[#This Row],[Initial Risk $]]/Tabla1[[#This Row],[Position Size (shares)]]*3+Tabla1[[#This Row],[Entry Price]] -> 108.87
A8: ="T-"& TEXT(ROW()-1,"000") -> T-007 | B8: 46079 | C8: OKLO | D8: Long | E8: CT Reversal | F8: 67.82 | G8: 58.5 | H8: =Tabla1[[#This Row],[Entry Price]]-(Tabla1[[#This Row],[Entry Price]]-Tabla1[[#This Row],[Initial Stop]])/2 -> 63.16 | I8: 3 | J8: =IF(D8="Long",(F8-G8)*I8,(G8-F8)*0) -> 27.96 | K8: 2 | L8: =J8*K8 -> 55.92 | M8: Closed | N8: =SUMIF(Executions!B:B,A8,Executions!H:H) -> -28.17 | O8: =N8/J8 -> -1.0075107 | P8: =Tabla1[[#This Row],[Initial Risk $]]/Tabla1[[#This Row],[Position Size (shares)]]+Tabla1[[#This Row],[Entry Price]] -> 77.14 | Q8: =Tabla1[[#This Row],[Initial Risk $]]/Tabla1[[#This Row],[Position Size (shares)]]*1.5+Tabla1[[#This Row],[Entry Price]] -> 81.8 | R8: =Tabla1[[#This Row],[Initial Risk $]]/Tabla1[[#This Row],[Position Size (shares)]]*2+Tabla1[[#This Row],[Entry Price]] -> 86.46 | S8: =Tabla1[[#This Row],[Initial Risk $]]/Tabla1[[#This Row],[Position Size (shares)]]*2.5+Tabla1[[#This Row],[Entry Price]] -> 91.12 | T8: =Tabla1[[#This Row],[Initial Risk $]]/Tabla1[[#This Row],[Position Size (shares)]]*3+Tabla1[[#This Row],[Entry Price]] -> 95.78
A9: ="T-"& TEXT(ROW()-1,"000") -> T-008 | B9: 46048 | C9: MNST | D9: Long | E9: Trend Continuation | F9: 75.67 | G9: 73.15 | H9: =Tabla1[[#This Row],[Entry Price]]-(Tabla1[[#This Row],[Entry Price]]-Tabla1[[#This Row],[Initial Stop]])/2 -> 74.41 | I9: 12 | J9: =IF(D9="Long",(F9-G9)*I9,(G9-F9)*0) -> 30.24 | K9: 2 | L9: =J9*K9 -> 60.48 | M9: Closed | N9: =SUMIF(Executions!B:B,A9,Executions!H:H) -> 80.4 | O9: =N9/J9 -> 2.6587302 | P9: =Tabla1[[#This Row],[Initial Risk $]]/Tabla1[[#This Row],[Position Size (shares)]]+Tabla1[[#This Row],[Entry Price]] -> 78.19 | Q9: =Tabla1[[#This Row],[Initial Risk $]]/Tabla1[[#This Row],[Position Size (shares)]]*1.5+Tabla1[[#This Row],[Entry Price]] -> 79.45 | R9: =Tabla1[[#This Row],[Initial Risk $]]/Tabla1[[#This Row],[Position Size (shares)]]*2+Tabla1[[#This Row],[Entry Price]] -> 80.71 | S9: =Tabla1[[#This Row],[Initial Risk $]]/Tabla1[[#This Row],[Position Size (shares)]]*2.5+Tabla1[[#This Row],[Entry Price]] -> 81.97 | T9: =Tabla1[[#This Row],[Initial Risk $]]/Tabla1[[#This Row],[Position Size (shares)]]*3+Tabla1[[#This Row],[Entry Price]] -> 83.23
A10: ="T-"& TEXT(ROW()-1,"000") -> T-009 | B10: 46083 | C10: UUUU | D10: Long | E10: Trend Continuation | F10: 22.46 | G10: 19.35 | H10: =Tabla1[[#This Row],[Entry Price]]-(Tabla1[[#This Row],[Entry Price]]-Tabla1[[#This Row],[Initial Stop]])/2 -> 20.905 | I10: 7 | J10: =IF(D10="Long",(F10-G10)*I10,(G10-F10)*0) -> 21.77 | K10: 2 | L10: =J10*K10 -> 43.54 | M10: Closed | N10: =SUMIF(Executions!B:B,A10,Executions!H:H) -> -25.445 | O10: =N10/J10 -> -1.1688103 | P10: =Tabla1[[#This Row],[Initial Risk $]]/Tabla1[[#This Row],[Position Size (shares)]]+Tabla1[[#This Row],[Entry Price]] -> 25.57 | Q10: =Tabla1[[#This Row],[Initial Risk $]]/Tabla1[[#This Row],[Position Size (shares)]]*1.5+Tabla1[[#This Row],[Entry Price]] -> 27.125 | R10: =Tabla1[[#This Row],[Initial Risk $]]/Tabla1[[#This Row],[Position Size (shares)]]*2+Tabla1[[#This Row],[Entry Price]] -> 28.68 | S10: =Tabla1[[#This Row],[Initial Risk $]]/Tabla1[[#This Row],[Position Size (shares)]]*2.5+Tabla1[[#This Row],[Entry Price]] -> 30.235 | T10: =Tabla1[[#This Row],[Initial Risk $]]/Tabla1[[#This Row],[Position Size (shares)]]*3+Tabla1[[#This Row],[Entry Price]] -> 31.79
A11: ="T-"& TEXT(ROW()-1,"000") -> T-010 | B11: 46083 | C11: NRT | D11: Long | E11: Trend Continuation | F11: 8.99 | G11: 8.16 | H11: =Tabla1[[#This Row],[Entry Price]]-(Tabla1[[#This Row],[Entry Price]]-Tabla1[[#This Row],[Initial Stop]])/2 -> 8.575 | I11: 27 | J11: =IF(D11="Long",(F11-G11)*I11,(G11-F11)*0) -> 22.41 | K11: 2 | L11: =J11*K11 -> 44.82 | M11: Closed | N11: =SUMIF(Executions!B:B,A11,Executions!H:H) -> 4.05 | O11: =N11/J11 -> 0.18072289 | P11: =Tabla1[[#This Row],[Initial Risk $]]/Tabla1[[#This Row],[Position Size (shares)]]+Tabla1[[#This Row],[Entry Price]] -> 9.82 | Q11: =Tabla1[[#This Row],[Initial Risk $]]/Tabla1[[#This Row],[Position Size (shares)]]*1.5+Tabla1[[#This Row],[Entry Price]] -> 10.235 | R11: =Tabla1[[#This Row],[Initial Risk $]]/Tabla1[[#This Row],[Position Size (shares)]]*2+Tabla1[[#This Row],[Entry Price]] -> 10.65 | S11: =Tabla1[[#This Row],[Initial Risk $]]/Tabla1[[#This Row],[Position Size (shares)]]*2.5+Tabla1[[#This Row],[Entry Price]] -> 11.065 | T11: =Tabla1[[#This Row],[Initial Risk $]]/Tabla1[[#This Row],[Position Size (shares)]]*3+Tabla1[[#This Row],[Entry Price]] -> 11.48
A12: ="T-"& TEXT(ROW()-1,"000") -> T-011 | B12: 46084 | C12: TJX | D12: Long | E12: Breakout | F12: 152.17 | G12: 150.48 | H12: =Tabla1[[#This Row],[Entry Price]]-(Tabla1[[#This Row],[Entry Price]]-Tabla1[[#This Row],[Initial Stop]])/2 -> 151.325 | I12: 6 | J12: =IF(D12="Long",(F12-G12)*I12,(G12-F12)*0) -> 10.14 | K12: 2 | L12: =J12*K12 -> 20.28 | M12: Closed | N12: =SUMIF(Executions!B:B,A12,Executions!H:H) -> 24.42 | O12: =N12/J12 -> 2.408284 | P12: =Tabla1[[#This Row],[Initial Risk $]]/Tabla1[[#This Row],[Position Size (shares)]]+Tabla1[[#This Row],[Entry Price]] -> 153.86 | Q12: =Tabla1[[#This Row],[Initial Risk $]]/Tabla1[[#This Row],[Position Size (shares)]]*1.5+Tabla1[[#This Row],[Entry Price]] -> 154.705 | R12: =Tabla1[[#This Row],[Initial Risk $]]/Tabla1[[#This Row],[Position Size (shares)]]*2+Tabla1[[#This Row],[Entry Price]] -> 155.55 | S12: =Tabla1[[#This Row],[Initial Risk $]]/Tabla1[[#This Row],[Position Size (shares)]]*2.5+Tabla1[[#This Row],[Entry Price]] -> 156.395 | T12: =Tabla1[[#This Row],[Initial Risk $]]/Tabla1[[#This Row],[Position Size (shares)]]*3+Tabla1[[#This Row],[Entry Price]] -> 157.24
A13: ="T-"& TEXT(ROW()-1,"000") -> T-012 | B13: 46085 | C13: APPS | D13: Long | E13: CT Reversal | F13: 4.27 | G13: 3.75 | H13: =Tabla1[[#This Row],[Entry Price]]-(Tabla1[[#This Row],[Entry Price]]-Tabla1[[#This Row],[Initial Stop]])/2 -> 4.01 | I13: 42 | J13: =IF(D13="Long",(F13-G13)*I13,(G13-F13)*0) -> 21.84 | K13: 2 | L13: =J13*K13 -> 43.68 | M13: Closed | N13: =SUMIF(Executions!B:B,A13,Executions!H:H) -> -24.78 | O13: =N13/J13 -> -1.1346154 | P13: =Tabla1[[#This Row],[Initial Risk $]]/Tabla1[[#This Row],[Position Size (shares)]]+Tabla1[[#This Row],[Entry Price]] -> 4.79 | Q13: =Tabla1[[#This Row],[Initial Risk $]]/Tabla1[[#This Row],[Position Size (shares)]]*1.5+Tabla1[[#This Row],[Entry Price]] -> 5.05 | R13: =Tabla1[[#This Row],[Initial Risk $]]/Tabla1[[#This Row],[Position Size (shares)]]*2+Tabla1[[#This Row],[Entry Price]] -> 5.31 | S13: =Tabla1[[#This Row],[Initial Risk $]]/Tabla1[[#This Row],[Position Size (shares)]]*2.5+Tabla1[[#This Row],[Entry Price]] -> 5.57 | T13: =Tabla1[[#This Row],[Initial Risk $]]/Tabla1[[#This Row],[Position Size (shares)]]*3+Tabla1[[#This Row],[Entry Price]] -> 5.83
... A501: ="T-"& TEXT(ROW()-1,"000") -> T-500 | B501: 46220 | C501: APP | D501: Long | E501: Mean reversion | F501: 423.33 | G501: 416 | H501: =Tabla1[[#This Row],[Entry Price]]-(Tabla1[[#This Row],[Entry Price]]-Tabla1[[#This Row],[Initial Stop]])/2 -> 419.665 | I501: 6 | J501: =IF(D501="Long",(F501-G501)*I501,(G501-F501)*0) -> 43.98 | K501: 1 | L501: =J501*K501 -> 43.98 | M501: Closed | N501: =SUMIF(Executions!B:B,A501,Executions!H:H) -> 42.48 | O501: =N501/J501 -> 0.96589359 | P501: =Tabla1[[#This Row],[Initial Risk $]]/Tabla1[[#This Row],[Position Size (shares)]]+Tabla1[[#This Row],[Entry Price]] -> 430.66 | Q501: =Tabla1[[#This Row],[Initial Risk $]]/Tabla1[[#This Row],[Position Size (shares)]]*1.5+Tabla1[[#This Row],[Entry Price]] -> 434.325 | R501: =Tabla1[[#This Row],[Initial Risk $]]/Tabla1[[#This Row],[Position Size (shares)]]*2+Tabla1[[#This Row],[Entry Price]] -> 437.99 | S501: =Tabla1[[#This Row],[Initial Risk $]]/Tabla1[[#This Row],[Position Size (shares)]]*2.5+Tabla1[[#This Row],[Entry Price]] -> 441.655 | T501: =Tabla1[[#This Row],[Initial Risk $]]/Tabla1[[#This Row],[Position Size (shares)]]*3+Tabla1[[#This Row],[Entry Price]] -> 445.32
A502: ="T-"& TEXT(ROW()-1,"000") -> T-501 | B502: 46220 | C502: MAN | D502: Long | E502: Mean reversion | F502: 54.84 | G502: 54.24 | H502: =Tabla1[[#This Row],[Entry Price]]-(Tabla1[[#This Row],[Entry Price]]-Tabla1[[#This Row],[Initial Stop]])/2 -> 54.54 | I502: 10 | J502: =IF(D502="Long",(F502-G502)*I502,(G502-F502)*0) -> 6 | L502: =J502*K502 -> 0 | M502: Closed | N502: =SUMIF(Executions!B:B,A502,Executions!H:H) -> -6.6 | O502: =N502/J502 -> -1.1 | P502: =Tabla1[[#This Row],[Initial Risk $]]/Tabla1[[#This Row],[Position Size (shares)]]+Tabla1[[#This Row],[Entry Price]] -> 55.44 | Q502: =Tabla1[[#This Row],[Initial Risk $]]/Tabla1[[#This Row],[Position Size (shares)]]*1.5+Tabla1[[#This Row],[Entry Price]] -> 55.74 | R502: =Tabla1[[#This Row],[Initial Risk $]]/Tabla1[[#This Row],[Position Size (shares)]]*2+Tabla1[[#This Row],[Entry Price]] -> 56.04 | S502: =Tabla1[[#This Row],[Initial Risk $]]/Tabla1[[#This Row],[Position Size (shares)]]*2.5+Tabla1[[#This Row],[Entry Price]] -> 56.34 | T502: =Tabla1[[#This Row],[Initial Risk $]]/Tabla1[[#This Row],[Position Size (shares)]]*3+Tabla1[[#This Row],[Entry Price]] -> 56.64
A503: ="T-"& TEXT(ROW()-1,"000") -> T-502 | B503: 46220 | C503: MU | D503: Long | E503: Mean reversion | F503: 854.48 | G503: 846 | H503: =Tabla1[[#This Row],[Entry Price]]-(Tabla1[[#This Row],[Entry Price]]-Tabla1[[#This Row],[Initial Stop]])/2 -> 850.24 | I503: 1 | J503: =IF(D503="Long",(F503-G503)*I503,(G503-F503)*0) -> 8.48 | K503: 1 | L503: =J503*K503 -> 8.48 | M503: Closed | N503: =SUMIF(Executions!B:B,A503,Executions!H:H) -> 33.21 | O503: =N503/J503 -> 3.9162736 | P503: =Tabla1[[#This Row],[Initial Risk $]]/Tabla1[[#This Row],[Position Size (shares)]]+Tabla1[[#This Row],[Entry Price]] -> 862.96 | Q503: =Tabla1[[#This Row],[Initial Risk $]]/Tabla1[[#This Row],[Position Size (shares)]]*1.5+Tabla1[[#This Row],[Entry Price]] -> 867.2 | R503: =Tabla1[[#This Row],[Initial Risk $]]/Tabla1[[#This Row],[Position Size (shares)]]*2+Tabla1[[#This Row],[Entry Price]] -> 871.44 | S503: =Tabla1[[#This Row],[Initial Risk $]]/Tabla1[[#This Row],[Position Size (shares)]]*2.5+Tabla1[[#This Row],[Entry Price]] -> 875.68 | T503: =Tabla1[[#This Row],[Initial Risk $]]/Tabla1[[#This Row],[Position Size (shares)]]*3+Tabla1[[#This Row],[Entry Price]] -> 879.92
A504: ="T-"& TEXT(ROW()-1,"000") -> T-503 | B504: 46223 | C504: AMZN | D504: Long | E504: Trend Continuation | F504: 249.36 | G504: 248 | H504: =Tabla1[[#This Row],[Entry Price]]-(Tabla1[[#This Row],[Entry Price]]-Tabla1[[#This Row],[Initial Stop]])/2 -> 248.68 | I504: 5 | J504: =IF(D504="Long",(F504-G504)*I504,(G504-F504)*0) -> 6.8 | K504: 1 | L504: =J504*K504 -> 6.8 | M504: Closed | N504: =SUMIF(Executions!B:B,A504,Executions!H:H) -> 13.05 | O504: =N504/J504 -> 1.9191176 | P504: =Tabla1[[#This Row],[Initial Risk $]]/Tabla1[[#This Row],[Position Size (shares)]]+Tabla1[[#This Row],[Entry Price]] -> 250.72 | Q504: =Tabla1[[#This Row],[Initial Risk $]]/Tabla1[[#This Row],[Position Size (shares)]]*1.5+Tabla1[[#This Row],[Entry Price]] -> 251.4 | R504: =Tabla1[[#This Row],[Initial Risk $]]/Tabla1[[#This Row],[Position Size (shares)]]*2+Tabla1[[#This Row],[Entry Price]] -> 252.08 | S504: =Tabla1[[#This Row],[Initial Risk $]]/Tabla1[[#This Row],[Position Size (shares)]]*2.5+Tabla1[[#This Row],[Entry Price]] -> 252.76 | T504: =Tabla1[[#This Row],[Initial Risk $]]/Tabla1[[#This Row],[Position Size (shares)]]*3+Tabla1[[#This Row],[Entry Price]] -> 253.44
A505: ="T-"& TEXT(ROW()-1,"000") -> T-504 | B505: 46223 | C505: GTLB | D505: Long | E505: Trend Continuation | F505: 32.57 | G505: 31.75 | H505: =Tabla1[[#This Row],[Entry Price]]-(Tabla1[[#This Row],[Entry Price]]-Tabla1[[#This Row],[Initial Stop]])/2 -> 32.16 | I505: 10 | J505: =IF(D505="Long",(F505-G505)*I505,(G505-F505)*0) -> 8.2 | K505: 1 | L505: =J505*K505 -> 8.2 | M505: Closed | N505: =SUMIF(Executions!B:B,A505,Executions!H:H) -> 8.5 | O505: =N505/J505 -> 1.0365854 | P505: =Tabla1[[#This Row],[Initial Risk $]]/Tabla1[[#This Row],[Position Size (shares)]]+Tabla1[[#This Row],[Entry Price]] -> 33.39 | Q505: =Tabla1[[#This Row],[Initial Risk $]]/Tabla1[[#This Row],[Position Size (shares)]]*1.5+Tabla1[[#This Row],[Entry Price]] -> 33.8 | R505: =Tabla1[[#This Row],[Initial Risk $]]/Tabla1[[#This Row],[Position Size (shares)]]*2+Tabla1[[#This Row],[Entry Price]] -> 34.21 | S505: =Tabla1[[#This Row],[Initial Risk $]]/Tabla1[[#This Row],[Position Size (shares)]]*2.5+Tabla1[[#This Row],[Entry Price]] -> 34.62 | T505: =Tabla1[[#This Row],[Initial Risk $]]/Tabla1[[#This Row],[Position Size (shares)]]*3+Tabla1[[#This Row],[Entry Price]] -> 35.03
A506: ="T-"& TEXT(ROW()-1,"000") -> T-505 | B506: 46223 | C506: AMD | D506: Long | E506: Trend Continuation | F506: 515.81 | G506: 510 | H506: =Tabla1[[#This Row],[Entry Price]]-(Tabla1[[#This Row],[Entry Price]]-Tabla1[[#This Row],[Initial Stop]])/2 -> 512.905 | I506: 4 | J506: =IF(D506="Long",(F506-G506)*I506,(G506-F506)*0) -> 23.24 | K506: 1 | L506: =J506*K506 -> 23.24 | M506: Closed | N506: =SUMIF(Executions!B:B,A506,Executions!H:H) -> -7.04 | O506: =N506/J506 -> -0.30292599 | P506: =Tabla1[[#This Row],[Initial Risk $]]/Tabla1[[#This Row],[Position Size (shares)]]+Tabla1[[#This Row],[Entry Price]] -> 521.62 | Q506: =Tabla1[[#This Row],[Initial Risk $]]/Tabla1[[#This Row],[Position Size (shares)]]*1.5+Tabla1[[#This Row],[Entry Price]] -> 524.525 | R506: =Tabla1[[#This Row],[Initial Risk $]]/Tabla1[[#This Row],[Position Size (shares)]]*2+Tabla1[[#This Row],[Entry Price]] -> 527.43 | S506: =Tabla1[[#This Row],[Initial Risk $]]/Tabla1[[#This Row],[Position Size (shares)]]*2.5+Tabla1[[#This Row],[Entry Price]] -> 530.335 | T506: =Tabla1[[#This Row],[Initial Risk $]]/Tabla1[[#This Row],[Position Size (shares)]]*3+Tabla1[[#This Row],[Entry Price]] -> 533.24
A507: ="T-"& TEXT(ROW()-1,"000") -> T-506 | B507: 46223 | C507: HPQ | D507: Long | E507: Trend Continuation | F507: 24.32 | G507: 24.15 | H507: =Tabla1[[#This Row],[Entry Price]]-(Tabla1[[#This Row],[Entry Price]]-Tabla1[[#This Row],[Initial Stop]])/2 -> 24.235 | I507: 40 | J507: =IF(D507="Long",(F507-G507)*I507,(G507-F507)*0) -> 6.8 | K507: 1 | L507: =J507*K507 -> 6.8 | M507: Closed | N507: =SUMIF(Executions!B:B,A507,Executions!H:H) -> -4.8 | O507: =N507/J507 -> -0.70588235 | P507: =Tabla1[[#This Row],[Initial Risk $]]/Tabla1[[#This Row],[Position Size (shares)]]+Tabla1[[#This Row],[Entry Price]] -> 24.49 | Q507: =Tabla1[[#This Row],[Initial Risk $]]/Tabla1[[#This Row],[Position Size (shares)]]*1.5+Tabla1[[#This Row],[Entry Price]] -> 24.575 | R507: =Tabla1[[#This Row],[Initial Risk $]]/Tabla1[[#This Row],[Position Size (shares)]]*2+Tabla1[[#This Row],[Entry Price]] -> 24.66 | S507: =Tabla1[[#This Row],[Initial Risk $]]/Tabla1[[#This Row],[Position Size (shares)]]*2.5+Tabla1[[#This Row],[Entry Price]] -> 24.745 | T507: =Tabla1[[#This Row],[Initial Risk $]]/Tabla1[[#This Row],[Position Size (shares)]]*3+Tabla1[[#This Row],[Entry Price]] -> 24.83
A508: ="T-"& TEXT(ROW()-1,"000") -> T-507 | B508: 46223 | C508: META | D508: Long | E508: Mean reversion | F508: 642.67 | G508: 638 | H508: =Tabla1[[#This Row],[Entry Price]]-(Tabla1[[#This Row],[Entry Price]]-Tabla1[[#This Row],[Initial Stop]])/2 -> 640.335 | I508: 2 | J508: =IF(D508="Long",(F508-G508)*I508,(G508-F508)*0) -> 9.34 | K508: 1 | L508: =J508*K508 -> 9.34 | M508: Closed | N508: =SUMIF(Executions!B:B,A508,Executions!H:H) -> 10.04 | O508: =N508/J508 -> 1.0749465 | P508: =Tabla1[[#This Row],[Initial Risk $]]/Tabla1[[#This Row],[Position Size (shares)]]+Tabla1[[#This Row],[Entry Price]] -> 647.34 | Q508: =Tabla1[[#This Row],[Initial Risk $]]/Tabla1[[#This Row],[Position Size (shares)]]*1.5+Tabla1[[#This Row],[Entry Price]] -> 649.675 | R508: =Tabla1[[#This Row],[Initial Risk $]]/Tabla1[[#This Row],[Position Size (shares)]]*2+Tabla1[[#This Row],[Entry Price]] -> 652.01 | S508: =Tabla1[[#This Row],[Initial Risk $]]/Tabla1[[#This Row],[Position Size (shares)]]*2.5+Tabla1[[#This Row],[Entry Price]] -> 654.345 | T508: =Tabla1[[#This Row],[Initial Risk $]]/Tabla1[[#This Row],[Position Size (shares)]]*3+Tabla1[[#This Row],[Entry Price]] -> 656.68
A509: ="T-"& TEXT(ROW()-1,"000") -> T-508 | B509: 46223 | C509: MU | D509: Long | E509: Reversal | F509: 878 | G509: 870 | H509: =Tabla1[[#This Row],[Entry Price]]-(Tabla1[[#This Row],[Entry Price]]-Tabla1[[#This Row],[Initial Stop]])/2 -> 874 | I509: 1 | J509: =IF(D509="Long",(F509-G509)*I509,(G509-F509)*0) -> 8 | K509: 1 | L509: =J509*K509 -> 8 | M509: Closed | N509: =SUMIF(Executions!B:B,A509,Executions!H:H) -> 18.03 | O509: =N509/J509 -> 2.25375 | P509: =Tabla1[[#This Row],[Initial Risk $]]/Tabla1[[#This Row],[Position Size (shares)]]+Tabla1[[#This Row],[Entry Price]] -> 886 | Q509: =Tabla1[[#This Row],[Initial Risk $]]/Tabla1[[#This Row],[Position Size (shares)]]*1.5+Tabla1[[#This Row],[Entry Price]] -> 890 | R509: =Tabla1[[#This Row],[Initial Risk $]]/Tabla1[[#This Row],[Position Size (shares)]]*2+Tabla1[[#This Row],[Entry Price]] -> 894 | S509: =Tabla1[[#This Row],[Initial Risk $]]/Tabla1[[#This Row],[Position Size (shares)]]*2.5+Tabla1[[#This Row],[Entry Price]] -> 898 | T509: =Tabla1[[#This Row],[Initial Risk $]]/Tabla1[[#This Row],[Position Size (shares)]]*3+Tabla1[[#This Row],[Entry Price]] -> 902
A510: ="T-"& TEXT(ROW()-1,"000") -> T-509 | B510: 46224 | C510: PATH | D510: Long | E510: Trend Continuation | F510: 12.46 | G510: 12.15 | H510: =Tabla1[[#This Row],[Entry Price]]-(Tabla1[[#This Row],[Entry Price]]-Tabla1[[#This Row],[Initial Stop]])/2 -> 12.305 | I510: 30 | J510: =IF(D510="Long",(F510-G510)*I510,(G510-F510)*0) -> 9.3 | K510: 1 | L510: =J510*K510 -> 9.3 | M510: Closed | N510: =SUMIF(Executions!B:B,A510,Executions!H:H) -> -9.3 | O510: =N510/J510 -> -1 | P510: =Tabla1[[#This Row],[Initial Risk $]]/Tabla1[[#This Row],[Position Size (shares)]]+Tabla1[[#This Row],[Entry Price]] -> 12.77 | Q510: =Tabla1[[#This Row],[Initial Risk $]]/Tabla1[[#This Row],[Position Size (shares)]]*1.5+Tabla1[[#This Row],[Entry Price]] -> 12.925 | R510: =Tabla1[[#This Row],[Initial Risk $]]/Tabla1[[#This Row],[Position Size (shares)]]*2+Tabla1[[#This Row],[Entry Price]] -> 13.08 | S510: =Tabla1[[#This Row],[Initial Risk $]]/Tabla1[[#This Row],[Position Size (shares)]]*2.5+Tabla1[[#This Row],[Entry Price]] -> 13.235 | T510: =Tabla1[[#This Row],[Initial Risk $]]/Tabla1[[#This Row],[Position Size (shares)]]*3+Tabla1[[#This Row],[Entry Price]] -> 13.39
A511: ="T-"& TEXT(ROW()-1,"000") -> T-510 | B511: 46224 | C511: AMD | D511: Long | E511: Trend Continuation | F511: 528.54 | G511: 523.54 | H511: =Tabla1[[#This Row],[Entry Price]]-(Tabla1[[#This Row],[Entry Price]]-Tabla1[[#This Row],[Initial Stop]])/2 -> 526.04 | I511: 2 | J511: =IF(D511="Long",(F511-G511)*I511,(G511-F511)*0) -> 10 | K511: 1 | L511: =J511*K511 -> 10 | M511: Closed | N511: =SUMIF(Executions!B:B,A511,Executions!H:H) -> -10.06 | O511: =N511/J511 -> -1.006 | P511: =Tabla1[[#This Row],[Initial Risk $]]/Tabla1[[#This Row],[Position Size (shares)]]+Tabla1[[#This Row],[Entry Price]] -> 533.54 | Q511: =Tabla1[[#This Row],[Initial Risk $]]/Tabla1[[#This Row],[Position Size (shares)]]*1.5+Tabla1[[#This Row],[Entry Price]] -> 536.04 | R511: =Tabla1[[#This Row],[Initial Risk $]]/Tabla1[[#This Row],[Position Size (shares)]]*2+Tabla1[[#This Row],[Entry Price]] -> 538.54 | S511: =Tabla1[[#This Row],[Initial Risk $]]/Tabla1[[#This Row],[Position Size (shares)]]*2.5+Tabla1[[#This Row],[Entry Price]] -> 541.04 | T511: =Tabla1[[#This Row],[Initial Risk $]]/Tabla1[[#This Row],[Position Size (shares)]]*3+Tabla1[[#This Row],[Entry Price]] -> 543.54
A512: ="T-"& TEXT(ROW()-1,"000") -> T-511 | B512: 46224 | C512: PYPL | D512: Long | E512: Mean reversion | F512: 56.27 | G512: 55.81 | H512: =Tabla1[[#This Row],[Entry Price]]-(Tabla1[[#This Row],[Entry Price]]-Tabla1[[#This Row],[Initial Stop]])/2 -> 56.04 | I512: 10 | J512: =IF(D512="Long",(F512-G512)*I512,(G512-F512)*0) -> 4.6 | K512: 1 | L512: =J512*K512 -> 4.6 | M512: Closed | N512: =SUMIF(Executions!B:B,A512,Executions!H:H) -> -4.6 | O512: =N512/J512 -> -1 | P512: =Tabla1[[#This Row],[Initial Risk $]]/Tabla1[[#This Row],[Position Size (shares)]]+Tabla1[[#This Row],[Entry Price]] -> 56.73 | Q512: =Tabla1[[#This Row],[Initial Risk $]]/Tabla1[[#This Row],[Position Size (shares)]]*1.5+Tabla1[[#This Row],[Entry Price]] -> 56.96 | R512: =Tabla1[[#This Row],[Initial Risk $]]/Tabla1[[#This Row],[Position Size (shares)]]*2+Tabla1[[#This Row],[Entry Price]] -> 57.19 | S512: =Tabla1[[#This Row],[Initial Risk $]]/Tabla1[[#This Row],[Position Size (shares)]]*2.5+Tabla1[[#This Row],[Entry Price]] -> 57.42 | T512: =Tabla1[[#This Row],[Initial Risk $]]/Tabla1[[#This Row],[Position Size (shares)]]*3+Tabla1[[#This Row],[Entry Price]] -> 57.65
A513: ="T-"& TEXT(ROW()-1,"000") -> T-512 | B513: 46224 | C513: AAPL | D513: Long | E513: Mean reversion | F513: 324.51 | G513: 322.51 | H513: =Tabla1[[#This Row],[Entry Price]]-(Tabla1[[#This Row],[Entry Price]]-Tabla1[[#This Row],[Initial Stop]])/2 -> 323.51 | I513: 3 | J513: =IF(D513="Long",(F513-G513)*I513,(G513-F513)*0) -> 6 | K513: 1 | L513: =J513*K513 -> 6 | M513: Closed | N513: =SUMIF(Executions!B:B,A513,Executions!H:H) -> 6.9 | O513: =N513/J513 -> 1.15 | P513: =Tabla1[[#This Row],[Initial Risk $]]/Tabla1[[#This Row],[Position Size (shares)]]+Tabla1[[#This Row],[Entry Price]] -> 326.51 | Q513: =Tabla1[[#This Row],[Initial Risk $]]/Tabla1[[#This Row],[Position Size (shares)]]*1.5+Tabla1[[#This Row],[Entry Price]] -> 327.51 | R513: =Tabla1[[#This Row],[Initial Risk $]]/Tabla1[[#This Row],[Position Size (shares)]]*2+Tabla1[[#This Row],[Entry Price]] -> 328.51 | S513: =Tabla1[[#This Row],[Initial Risk $]]/Tabla1[[#This Row],[Position Size (shares)]]*2.5+Tabla1[[#This Row],[Entry Price]] -> 329.51 | T513: =Tabla1[[#This Row],[Initial Risk $]]/Tabla1[[#This Row],[Position Size (shares)]]*3+Tabla1[[#This Row],[Entry Price]] -> 330.51
A514: ="T-"& TEXT(ROW()-1,"000") -> T-513 | B514: 46224 | C514: AMD | D514: Long | E514: Mean reversion | F514: 528.91 | G514: 523 | H514: =Tabla1[[#This Row],[Entry Price]]-(Tabla1[[#This Row],[Entry Price]]-Tabla1[[#This Row],[Initial Stop]])/2 -> 525.955 | I514: 2 | J514: =IF(D514="Long",(F514-G514)*I514,(G514-F514)*0) -> 11.82 | K514: 1 | L514: =J514*K514 -> 11.82 | M514: Closed | N514: =SUMIF(Executions!B:B,A514,Executions!H:H) -> 23.64 | O514: =N514/J514 -> 2 | P514: =Tabla1[[#This Row],[Initial Risk $]]/Tabla1[[#This Row],[Position Size (shares)]]+Tabla1[[#This Row],[Entry Price]] -> 534.82 | Q514: =Tabla1[[#This Row],[Initial Risk $]]/Tabla1[[#This Row],[Position Size (shares)]]*1.5+Tabla1[[#This Row],[Entry Price]] -> 537.775 | R514: =Tabla1[[#This Row],[Initial Risk $]]/Tabla1[[#This Row],[Position Size (shares)]]*2+Tabla1[[#This Row],[Entry Price]] -> 540.73 | S514: =Tabla1[[#This Row],[Initial Risk $]]/Tabla1[[#This Row],[Position Size (shares)]]*2.5+Tabla1[[#This Row],[Entry Price]] -> 543.685 | T514: =Tabla1[[#This Row],[Initial Risk $]]/Tabla1[[#This Row],[Position Size (shares)]]*3+Tabla1[[#This Row],[Entry Price]] -> 546.64
... A876: ="T-"& TEXT(ROW()-1,"000") -> T-875 | B876: 46283 | C876: AFRM | D876: Long | E876: Mean reversion | F876: 70.63 | G876: 69.58 | H876: =Tabla1[[#This Row],[Entry Price]]-(Tabla1[[#This Row],[Entry Price]]-Tabla1[[#This Row],[Initial Stop]])/2 -> 70.105 | I876: 10 | J876: =IF(D876="Long",(F876-G876)*I876,(G876-F876)*0) -> 10.5 | K876: 1 | L876: =J876*K876 -> 10.5 | M876: Closed | N876: =SUMIF(Executions!B:B,A876,Executions!H:H) -> 2.6 | O876: =N876/J876 -> 0.24761905 | P876: =Tabla1[[#This Row],[Initial Risk $]]/Tabla1[[#This Row],[Position Size (shares)]]+Tabla1[[#This Row],[Entry Price]] -> 71.68 | Q876: =Tabla1[[#This Row],[Initial Risk $]]/Tabla1[[#This Row],[Position Size (shares)]]*1.5+Tabla1[[#This Row],[Entry Price]] -> 72.205 | R876: =Tabla1[[#This Row],[Initial Risk $]]/Tabla1[[#This Row],[Position Size (shares)]]*2+Tabla1[[#This Row],[Entry Price]] -> 72.73 | S876: =Tabla1[[#This Row],[Initial Risk $]]/Tabla1[[#This Row],[Position Size (shares)]]*2.5+Tabla1[[#This Row],[Entry Price]] -> 73.255 | T876: =Tabla1[[#This Row],[Initial Risk $]]/Tabla1[[#This Row],[Position Size (shares)]]*3+Tabla1[[#This Row],[Entry Price]] -> 73.78

Sheet Executions
A1: Exec_ID | B1: Trade_ID | C1: Date | D1: Ticker | E1: Action | F1: Execution Price | G1: Shares Closed | H1: P&L | I1: R Contribution | K1: Estimated fee cost | L1: =1*COUNT(A:A) -> 904
A2: =ROW()-1 -> 1 | B2: T-001 | C2: 46077 | D2: =VLOOKUP(B2,Trades!A$1:N100794,3,FALSE) -> ONDS | E2: Sell | F2: 9.81 | G2: 18 | H2: =IF(VLOOKUP(B2,Trades!A:N,4,FALSE)="Long",(F2-VLOOKUP(B2,Trades!A:N,6,FALSE))*G2,(VLOOKUP(B2,Trades!A:N,6,FALSE)-F2)*G2) -> -23.4 | I2: =H2/VLOOKUP(B2,Trades!A$1:$N$100794,9,FALSE) -> -1.3
A3: =ROW()-1 -> 2 | B3: T-004 | C3: 46077 | D3: =VLOOKUP(B3,Trades!A$1:N100795,3,FALSE) -> NG | E3: Sell | F3: 11.765 | G3: 18 | H3: =IF(VLOOKUP(B3,Trades!A:N,4,FALSE)="Long",(F3-VLOOKUP(B3,Trades!A:N,6,FALSE))*G3,(VLOOKUP(B3,Trades!A:N,6,FALSE)-F3)*G3) -> 25.11 | I3: =H3/VLOOKUP(B3,Trades!A$1:$N$100794,9,FALSE) -> 0.6975
A4: =ROW()-1 -> 3 | B4: T-002 | C4: 46078 | D4: =VLOOKUP(B4,Trades!A$1:N100796,3,FALSE) -> DNN | E4: Sell | F4: 4.29 | G4: 61 | H4: =IF(VLOOKUP(B4,Trades!A:N,4,FALSE)="Long",(F4-VLOOKUP(B4,Trades!A:N,6,FALSE))*G4,(VLOOKUP(B4,Trades!A:N,6,FALSE)-F4)*G4) -> 6.71 | I4: =H4/VLOOKUP(B4,Trades!A$1:$N$100794,9,FALSE) -> 0.11
A5: =ROW()-1 -> 4 | B5: T-008 | C5: 46083 | D5: =VLOOKUP(B5,Trades!A$1:N100797,3,FALSE) -> MNST | E5: Sell | F5: 82.37 | G5: 12 | H5: =IF(VLOOKUP(B5,Trades!A:N,4,FALSE)="Long",(F5-VLOOKUP(B5,Trades!A:N,6,FALSE))*G5,(VLOOKUP(B5,Trades!A:N,6,FALSE)-F5)*G5) -> 80.4 | I5: =H5/VLOOKUP(B5,Trades!A$1:$N$100794,9,FALSE) -> 6.7
A6: =ROW()-1 -> 5 | B6: T-004 | C6: 46084 | D6: =VLOOKUP(B6,Trades!A$1:N100798,3,FALSE) -> NG | E6: Sell | F6: 12.27 | G6: 18 | H6: =IF(VLOOKUP(B6,Trades!A:N,4,FALSE)="Long",(F6-VLOOKUP(B6,Trades!A:N,6,FALSE))*G6,(VLOOKUP(B6,Trades!A:N,6,FALSE)-F6)*G6) -> 34.2 | I6: =H6/VLOOKUP(B6,Trades!A$1:$N$100794,9,FALSE) -> 0.95
A7: =ROW()-1 -> 6 | B7: T-011 | C7: 46084 | D7: =VLOOKUP(B7,Trades!A$1:N100799,3,FALSE) -> TJX | E7: Sell | F7: 156.24 | G7: 6 | H7: =IF(VLOOKUP(B7,Trades!A:N,4,FALSE)="Long",(F7-VLOOKUP(B7,Trades!A:N,6,FALSE))*G7,(VLOOKUP(B7,Trades!A:N,6,FALSE)-F7)*G7) -> 24.42 | I7: =H7/VLOOKUP(B7,Trades!A$1:$N$100794,9,FALSE) -> 4.07
A8: =ROW()-1 -> 7 | B8: T-005 | C8: 46085 | D8: =VLOOKUP(B8,Trades!A$1:N100800,3,FALSE) -> ATEC | E8: Sell | F8: 12.832 | G8: 19 | H8: =IF(VLOOKUP(B8,Trades!A:N,4,FALSE)="Long",(F8-VLOOKUP(B8,Trades!A:N,6,FALSE))*G8,(VLOOKUP(B8,Trades!A:N,6,FALSE)-F8)*G8) -> -10.602 | I8: =H8/VLOOKUP(B8,Trades!A$1:$N$100794,9,FALSE) -> -0.558
A9: =ROW()-1 -> 8 | B9: T-014 | C9: 46087 | D9: =VLOOKUP(B9,Trades!A$1:N100801,3,FALSE) -> LULU | E9: Sell | F9: 166.62 | G9: 2 | H9: =IF(VLOOKUP(B9,Trades!A:N,4,FALSE)="Long",(F9-VLOOKUP(B9,Trades!A:N,6,FALSE))*G9,(VLOOKUP(B9,Trades!A:N,6,FALSE)-F9)*G9) -> -21.72 | I9: =H9/VLOOKUP(B9,Trades!A$1:$N$100794,9,FALSE) -> -10.86
A10: =ROW()-1 -> 9 | B10: T-009 | C10: 46087 | D10: =VLOOKUP(B10,Trades!A$1:N100802,3,FALSE) -> UUUU | E10: Sell | F10: 18.825 | G10: 7 | H10: =IF(VLOOKUP(B10,Trades!A:N,4,FALSE)="Long",(F10-VLOOKUP(B10,Trades!A:N,6,FALSE))*G10,(VLOOKUP(B10,Trades!A:N,6,FALSE)-F10)*G10) -> -25.445 | I10: =H10/VLOOKUP(B10,Trades!A$1:$N$100794,9,FALSE) -> -3.635
A11: =ROW()-1 -> 10 | B11: T-007 | C11: 46087 | D11: =VLOOKUP(B11,Trades!A$1:N100803,3,FALSE) -> OKLO | E11: Sell | F11: 58.43 | G11: 3 | H11: =IF(VLOOKUP(B11,Trades!A:N,4,FALSE)="Long",(F11-VLOOKUP(B11,Trades!A:N,6,FALSE))*G11,(VLOOKUP(B11,Trades!A:N,6,FALSE)-F11)*G11) -> -28.17 | I11: =H11/VLOOKUP(B11,Trades!A$1:$N$100794,9,FALSE) -> -9.39
A12: =ROW()-1 -> 11 | B12: T-003 | C12: 46090 | D12: =VLOOKUP(B12,Trades!A$1:N100804,3,FALSE) -> TMDX | E12: Sell | F12: 125.27 | G12: 3 | H12: =IF(VLOOKUP(B12,Trades!A:N,4,FALSE)="Long",(F12-VLOOKUP(B12,Trades!A:N,6,FALSE))*G12,(VLOOKUP(B12,Trades!A:N,6,FALSE)-F12)*G12) -> -35.01 | I12: =H12/VLOOKUP(B12,Trades!A$1:$N$100794,9,FALSE) -> -11.67
A13: =ROW()-1 -> 12 | B13: T-012 | C13: 46093 | D13: =VLOOKUP(B13,Trades!A$1:N100805,3,FALSE) -> APPS | E13: Sell | F13: 3.68 | G13: 42 | H13: =IF(VLOOKUP(B13,Trades!A:N,4,FALSE)="Long",(F13-VLOOKUP(B13,Trades!A:N,6,FALSE))*G13,(VLOOKUP(B13,Trades!A:N,6,FALSE)-F13)*G13) -> -24.78 | I13: =H13/VLOOKUP(B13,Trades!A$1:$N$100794,9,FALSE) -> -0.59
... A905: =ROW()-1 -> 904 | B905: T-875 | C905: 46283 | D905: =VLOOKUP(B905,Trades!A$1:N101697,3,FALSE) -> AFRM | E905: Sell | F905: 70.89 | G905: 10 | H905: =IF(VLOOKUP(B905,Trades!A:N,4,FALSE)="Long",(F905-VLOOKUP(B905,Trades!A:N,6,FALSE))*G905,(VLOOKUP(B905,Trades!A:N,6,FALSE)-F905)*G905) -> 2.6 | I905: =H905/VLOOKUP(B905,Trades!A$1:$N$100794,9,FALSE) -> 0.26

Sheet Setups
A1: Setup Name | B1: Total Trades | C1: Wins | D1: Losses | E1: Win Rate | F1: Total R | G1: Avg R per Trade | H1: Profit Factor | I1: Expectancy
A2: Breakout | B2: =COUNTIF(Trades!E:E,A2) -> 6 | C2: =COUNTIFS(Trades!E:E, A2,Trades!N:N, ">0") -> 2 | D2: =COUNTIFS(Trades!E:E, A2, Trades!N:N, "<0") -> 4 | E2: =IFERROR(C2/B2,0) -> 0.33333333 | F2: =SUMIF(Trades!E:E,A2,Trades!O:O) -> 1.3303423 | G2: =IFERROR(F2/B2,0) -> 0.22172372 | H2: =IFERROR( SUMIFS(Trades!N:N, Trades!E:E, A2, Trades!N:N, ">0")/ABS(SUMIFS(Trades!N:N,Trades!E:E, A2,Trades!N:N,"<0")),0) -> 1.7119199 | I2: =IFERROR(F2/B2,0) -> 0.22172372
A3: Pullback | B3: =COUNTIF(Trades!E:E,A3) -> 22 | C3: =COUNTIFS(Trades!E:E, A3,Trades!N:N, ">0") -> 6 | D3: =COUNTIFS(Trades!E:E, A3, Trades!N:N, "<0") -> 16 | E3: =IFERROR(C3/B3,0) -> 0.27272727 | F3: =SUMIF(Trades!E:E,A3,Trades!O:O) -> 2.4651702 | G3: =IFERROR(F3/B3,0) -> 0.11205319 | H3: =IFERROR( SUMIFS(Trades!N:N, Trades!E:E, A3, Trades!N:N, ">0")/ABS(SUMIFS(Trades!N:N, Trades!E:E, A3, Trades!N:N,"<0")),0) -> 1.2277012 | I3: =IFERROR(F3/B3,0) -> 0.11205319
A4: Range Break | B4: =COUNTIF(Trades!E:E,A4) -> 12 | C4: =COUNTIFS(Trades!E:E, A4,Trades!N:N, ">0") -> 2 | D4: =COUNTIFS(Trades!E:E, A4, Trades!N:N, "<0") -> 10 | E4: =IFERROR(C4/B4,0) -> 0.16666667 | F4: =SUMIF(Trades!E:E,A4,Trades!O:O) -> -9.5633095 | G4: =IFERROR(F4/B4,0) -> -0.79694246 | H4: =IFERROR( SUMIFS(Trades!N:N, Trades!E:E, A4, Trades!N:N, ">0")/ABS(SUMIFS(Trades!N:N, Trades!E:E, A4, Trades!N:N,"<0")),0) -> 0.06234733 | I4: =IFERROR(F4/B4,0) -> -0.79694246
A5: Reversal | B5: =COUNTIF(Trades!E:E,A5) -> 82 | C5: =COUNTIFS(Trades!E:E, A5,Trades!N:N, ">0") -> 33 | D5: =COUNTIFS(Trades!E:E, A5, Trades!N:N, "<0") -> 48 | E5: =IFERROR(C5/B5,0) -> 0.40243902 | F5: =SUMIF(Trades!E:E,A5,Trades!O:O) -> -8.3656996 | G5: =IFERROR(F5/B5,0) -> -0.10202073 | H5: =IFERROR( SUMIFS(Trades!N:N, Trades!E:E, A5, Trades!N:N, ">0")/ABS(SUMIFS(Trades!N:N, Trades!E:E, A5, Trades!N:N,"<0")),0) -> 0.88476409 | I5: =IFERROR(F5/B5,0) -> -0.10202073
A6: Earning Play | B6: =COUNTIF(Trades!E:E,A6) -> 45 | C6: =COUNTIFS(Trades!E:E, A6,Trades!N:N, ">0") -> 15 | D6: =COUNTIFS(Trades!E:E, A6, Trades!N:N, "<0") -> 30 | E6: =IFERROR(C6/B6,0) -> 0.33333333 | F6: =SUMIF(Trades!E:E,A6,Trades!O:O) -> 13.060147 | G6: =IFERROR(F6/B6,0) -> 0.29022548 | H6: =IFERROR( SUMIFS(Trades!N:N, Trades!E:E, A6, Trades!N:N, ">0")/ABS(SUMIFS(Trades!N:N, Trades!E:E, A6, Trades!N:N,"<0")),0) -> 1.0007641 | I6: =IFERROR(F6/B6,0) -> 0.29022548
A7: A+ Setup | B7: =COUNTIF(Trades!E:E,A7) -> 7 | C7: =COUNTIFS(Trades!E:E, A7,Trades!N:N, ">0") -> 5 | D7: =COUNTIFS(Trades!E:E, A7, Trades!N:N, "<0") -> 2 | E7: =IFERROR(C7/B7,0) -> 0.71428571 | F7: =SUMIF(Trades!E:E,A7,Trades!O:O) -> 8.5561252 | G7: =IFERROR(F7/B7,0) -> 1.2223036 | H7: =IFERROR( SUMIFS(Trades!N:N, Trades!E:E, A7, Trades!N:N, ">0")/ABS(SUMIFS(Trades!N:N, Trades!E:E, A7, Trades!N:N,"<0")),0) -> 1.3783013 | I7: =IFERROR(F7/B7,0) -> 1.2223036
A8: A Setup | B8: =COUNTIF(Trades!E:E,A8) -> 5 | C8: =COUNTIFS(Trades!E:E, A8,Trades!N:N, ">0") -> 0 | D8: =COUNTIFS(Trades!E:E, A8, Trades!N:N, "<0") -> 5 | E8: =IFERROR(C8/B8,0) -> 0 | F8: =SUMIF(Trades!E:E,A8,Trades!O:O) -> -5.5879273 | G8: =IFERROR(F8/B8,0) -> -1.1175855 | H8: =IFERROR( SUMIFS(Trades!N:N, Trades!E:E, A8, Trades!N:N, ">0")/ABS(SUMIFS(Trades!N:N, Trades!E:E, A8, Trades!N:N,"<0")),0) -> 0 | I8: =IFERROR(F8/B8,0) -> -1.1175855
A9: B Setup | B9: =COUNTIF(Trades!E:E,A9) -> 0 | C9: =COUNTIFS(Trades!E:E, A9,Trades!N:N, ">0") -> 0 | D9: =COUNTIFS(Trades!E:E, A9, Trades!N:N, "<0") -> 0 | E9: =IFERROR(C9/B9,0) -> 0 | F9: =SUMIF(Trades!E:E,A9,Trades!O:O) -> 0 | G9: =IFERROR(F9/B9,0) -> 0 | H9: =IFERROR( SUMIFS(Trades!N:N, Trades!E:E, A9, Trades!N:N, ">0")/ABS(SUMIFS(Trades!N:N, Trades!E:E, A9, Trades!N:N,"<0")),0) -> 0 | I9: =IFERROR(F9/B9,0) -> 0
A10: Buy the Dip | B10: =COUNTIF(Trades!E:E,A10) -> 4 | C10: =COUNTIFS(Trades!E:E, A10,Trades!N:N, ">0") -> 1 | D10: =COUNTIFS(Trades!E:E, A10, Trades!N:N, "<0") -> 3 | E10: =IFERROR(C10/B10,0) -> 0.25 | F10: =SUMIF(Trades!E:E,A10,Trades!O:O) -> -0.94635211 | G10: =IFERROR(F10/B10,0) -> -0.23658803 | H10: =IFERROR( SUMIFS(Trades!N:N, Trades!E:E, A10, Trades!N:N, ">0")/ABS(SUMIFS(Trades!N:N, Trades!E:E, A10, Trades!N:N,"<0")),0) -> 0.088225118 | I10: =IFERROR(F10/B10,0) -> -0.23658803
A11: Trend Continuation | B11: =COUNTIF(Trades!E:E,A11) -> 435 | C11: =COUNTIFS(Trades!E:E, A11,Trades!N:N, ">0") -> 161 | D11: =COUNTIFS(Trades!E:E, A11, Trades!N:N, "<0") -> 272 | E11: =IFERROR(C11/B11,0) -> 0.37011494 | F11: =SUMIF(Trades!E:E,A11,Trades!O:O) -> 45.117817 | G11: =IFERROR(F11/B11,0) -> 0.10371912 | H11: =IFERROR( SUMIFS(Trades!N:N, Trades!E:E, A11, Trades!N:N, ">0")/ABS(SUMIFS(Trades!N:N, Trades!E:E, A11, Trades!N:N,"<0")),0) -> 1.0450799 | I11: =IFERROR(F11/B11,0) -> 0.10371912
A12: CT Reversal | B12: =COUNTIF(Trades!E:E,A12) -> 32 | C12: =COUNTIFS(Trades!E:E, A12,Trades!N:N, ">0") -> 5 | D12: =COUNTIFS(Trades!E:E, A12, Trades!N:N, "<0") -> 27 | E12: =IFERROR(C12/B12,0) -> 0.15625 | F12: =SUMIF(Trades!E:E,A12,Trades!O:O) -> -21.705442 | G12: =IFERROR(F12/B12,0) -> -0.67829507 | H12: =IFERROR( SUMIFS(Trades!N:N, Trades!E:E, A12, Trades!N:N, ">0")/ABS(SUMIFS(Trades!N:N, Trades!E:E, A12, Trades!N:N,"<0")),0) -> 0.11273933 | I12: =IFERROR(F12/B12,0) -> -0.67829507
A13: Short Squeeze | B13: =COUNTIF(Trades!E:E,A13) -> 2 | C13: =COUNTIFS(Trades!E:E, A13,Trades!N:N, ">0") -> 0 | D13: =COUNTIFS(Trades!E:E, A13, Trades!N:N, "<0") -> 1 | E13: =IFERROR(C13/B13,0) -> 0 | F13: =SUMIF(Trades!E:E,A13,Trades!O:O) -> -0.92996109 | G13: =IFERROR(F13/B13,0) -> -0.46498054 | H13: =IFERROR( SUMIFS(Trades!N:N, Trades!E:E, A13, Trades!N:N, ">0")/ABS(SUMIFS(Trades!N:N, Trades!E:E, A13, Trades!N:N,"<0")),0) -> 0 | I13: =IFERROR(F13/B13,0) -> -0.46498054
A14: Mean reversion | B14: =COUNTIF(Trades!E:E,A14) -> 221 | C14: =COUNTIFS(Trades!E:E, A14,Trades!N:N, ">0") -> 76 | D14: =COUNTIFS(Trades!E:E, A14, Trades!N:N, "<0") -> 145 | E14: =IFERROR(C14/B14,0) -> 0.3438914 | F14: =SUMIF(Trades!E:E,A14,Trades!O:O) -> -19.069512 | G14: =IFERROR(F14/B14,0) -> -0.086287383 | H14: =IFERROR( SUMIFS(Trades!N:N, Trades!E:E, A14, Trades!N:N, ">0")/ABS(SUMIFS(Trades!N:N, Trades!E:E, A14, Trades!N:N,"<0")),0) -> 0.91590507 | I14: =IFERROR(F14/B14,0) -> -0.086287383
A15: Other | B15: =COUNTIF(Trades!E:E,A15) -> 2 | C15: =COUNTIFS(Trades!E:E, A15,Trades!N:N, ">0") -> 2 | D15: =COUNTIFS(Trades!E:E, A15, Trades!N:N, "<0") -> 0 | E15: =IFERROR(C15/B15,0) -> 1 | F15: =SUMIF(Trades!E:E,A15,Trades!O:O) -> 3.833008 | G15: =IFERROR(F15/B15,0) -> 1.916504 | H15: =IFERROR( SUMIFS(Trades!N:N, Trades!E:E, A15, Trades!N:N, ">0")/ABS(SUMIFS(Trades!N:N, Trades!E:E, A15, Trades!N:N,"<0")),0) -> 0 | I15: =IFERROR(F15/B15,0) -> 1.916504

Sheet Mistakes
A1: Trade_ID | B1: Date | C1: Mistake_Type | D1: Preventable | E1: Cost in R | F1: Notes
A2: T-001 | B2: 46077 | C2: Technical | D2: No | E2: -1 | F2: MACD never got confirmation after a try for continuation
A3: T-002 | B3: 46078 | C3: Technical | D3: Yes | E3: 0 | F3: It was closed with earnings, but the entry was timed because I didn't consider earnings release
A4: T-015 | B4: 46098 | C4: Technical | D4: No | E4: 0 | F4: IHS is showing a recovery but todays earnings were negative I decided to exit before any negative move might happen if I lose the trend, be it, there is too much risk in current market environment
A5: T-018 | B5: 46101 | C5: Technical | D5: Yes | E5: -19.71 | F5: The market is really choppy and I didn't wait for confirmation, at the end, what it was looking as a potential bounce, finish by falling back, and not recovering.

Sheet Daily Journal
A1: Date | B1: Starting Balance | C1: Ending Equity | D1: Daily R | E1: Emotions | F1: Disciplince Score | G1: Market Contition | H1: Lessons | I1: Sleep Quality | J1: Focus Level
A2: 46077 | B2: 9076 | C2: 9117 | D2: =C2-B2 -> 41 | E2: Calm, reduce portfolio, but difficulty to find entries | F2: 4/5 | G2: Most indexes are green, VIX open above 20, but it dropped to 19, still high | H2: I sceened for entries all they long, but there is few A+ options, the market shows a lot of volatility | I2: Good | J2: High
A3: 46078 | B3: 9117 | C3: 9113 | D3: =C3-B3 -> -4 | E3: The stocks picked are holding the volatility, butit didn't grow | F3: 4/5 | G3: The indexes are gren again, VIX is around 18 levels | H3: It is important to consider earnings release before opening positions, today it was a couple of risky entry that luckily worked out | I3: Good | J3: Medium
A4: 46079 | B4: 9113 | C4: 9171 | D4: =C4-B4 -> 58 | E4: Several entries with .25 risk per trade, they seem to be in good momentum since I am trying to enter after bouncing | F4: 5/5 | G4: The market started green, but the earnings released by NVDA added more uncertainty about the AI and it has increased the volatility, VIX has gone over 20 again and the market is falling in general | H4: Patience for entries are everything | I4: Good | J4: High
A5: 46080 | B5: 9171 | C5: 9186 | D5: =C5-B5 -> 15 | E5: Despite the market falling, most of the stocks selected are showing strength I bought them from a relative slow aiming to a counter trend reversal or reversal, for the moment most of the stocks are working which leaves me at easy. Is pretty likely that the portfolio will drop during the day. At the end I manage to do a marginal increase of 15 bucks | F5: 5/5 | G5: Most of the market opened with a gap down, and it is mostly falling, VIX is over 20 again but this time there is no a clear trigger, most likely is related with AI concerns that have been increasing the volatility in recent | H5: Look for entries in the structure, not the price, it is what is working. | I5: Good | J5: Low
A6: 46098 | B6: 8855 | E6: I have trading really few regarding the last drops that the market has experienced, I feel really down, but I am avoiding any behavior that could compromise my capital | F6: 5/5 | G6: The war in Iran has caused the oil to pike and the market to go down, until last Friday, there were 6 consecutive red days for the main indexes in the market, it clearly hit me hard | I6: Good
A7: 46101 | B7: 8784

Sheet Dashboard
A1: Core Stats
A2: Total Trades: | B2: =COUNTA(Trades!A:A)-1 -> 875
A3: Win Rate: | B3: =COUNTIF(Trades!N:N,">0")/COUNT(Trades!N:N) -> 0.352
A4: Avg R: | B4: =AVERAGE(Trades!O:O) -> 0.0093650349
A5: Total R: | B5: =SUM(Trades!O:O) -> 8.1944056
A6: Profit Factor | B6: =SUMIF(Trades!N:N,">0")/ABS(SUM(Trades!N:N,""<0)) -> 12.016387
A7: Relaized P&L | B7: =SUM(Trades!N:N) -> -387.9086
A8: Total After fees | B8: =B7-Executions!L1 -> -1291.9086
A10: Risk Metrics
A11: Max Win: | B11: =MAX(Trades!N:N) -> 165.72
A12: Max Loss: | B12: =MIN(Trades!N:N) -> -155
A13: Avg Win: | B13: =AVERAGEIF(Trades!N:N,">0") -> 15.133961
A14: Avg Loss: | B14: =AVERAGEIF(Trades!N:N,"<0") -> -8.9683279
