Workbook

Sheet Trades
A1: Trade_ID | B1: Date Opened | C1: Ticker | D1: Direction | E1: Setup | F1: Entry Price | G1: Initial Stop | H1: Position Size (shares) | I1: Risk(R) | J1: Planned R Target | K1: Planned Profit Target | L1: Status | M1: Total Realized R
A2: ="T-"& TEXT(ROW()-1,"000") -> T-001 | B2: 46072 | C2: ONDS | D2: Long | E2: CT Reversal | F2: 11.11 | G2: 9.81 | H2: 18 | I2: =IF(D2="Long",(F2-G2)*H2,(G2-F2)*0) -> 23.4 | J2: 2 | K2: =I2*J2 -> 46.8 | L2: Closed | M2: =SUMIF(Executions!B:B,A2,Executions!H:H) -> -23.4
A3: ="T-"& TEXT(ROW()-1,"000") -> T-002 | B3: 46077 | C3: DNN | D3: Long | E3: Trend Continuation | F3: 4.18 | G3: 3.82 | H3: 61 | I3: =IF(D3="Long",(F3-G3)*H3,(G3-F3)*0) -> 21.96 | J3: 2 | K3: =I3*J3 -> 43.92 | L3: Closed | M3: =SUMIF(Executions!B:B,A3,Executions!H:H) -> 6.71
A4: ="T-"& TEXT(ROW()-1,"000") -> T-003 | B4: 46077 | C4: TMDX | D4: Long | E4: Breakout | F4: 136.94 | G4: 127.28 | H4: 3 | I4: =IF(D4="Long",(F4-G4)*H4,(G4-F4)*0) -> 28.98 | J4: 2 | K4: =I4*J4 -> 57.96 | L4: Open | M4: =SUMIF(Executions!B:B,A4,Executions!H:H) -> 0
A5: ="T-"& TEXT(ROW()-1,"000") -> T-004 | B5: 46070 | C5: NG | D5: Long | E5: Breakout | F5: 10.37 | G5: 9.45 | H5: 36 | I5: =IF(D5="Long",(F5-G5)*H5,(G5-F5)*0) -> 33.12 | J5: 1.5 | K5: =I5*J5 -> 49.68 | L5: Open | M5: =SUMIF(Executions!B:B,A5,Executions!H:H) -> 59.31
A6: ="T-"& TEXT(ROW()-1,"000") -> T-005 | B6: 46078 | C6: ATEC | D6: Long | E6: CT Reversal | F6: 13.39 | G6: 12.39 | H6: 19 | I6: =IF(D6="Long",(F6-G6)*H6,(G6-F6)*0) -> 19 | J6: 2 | K6: =I6*J6 -> 38 | L6: Closed | M6: =SUMIF(Executions!B:B,A6,Executions!H:H) -> -10.602
A7: ="T-"& TEXT(ROW()-1,"000") -> T-006 | B7: 46079 | C7: ROKU | D7: Long | E7: Reversal | F7: 92.49 | G7: 87.03 | H7: 3 | I7: =IF(D7="Long",(F7-G7)*H7,(G7-F7)*0) -> 16.38 | J7: 2 | K7: =I7*J7 -> 32.76 | L7: Open | M7: =SUMIF(Executions!B:B,A7,Executions!H:H) -> 0
A8: ="T-"& TEXT(ROW()-1,"000") -> T-007 | B8: 46079 | C8: OKLO | D8: Long | E8: CT Reversal | F8: 67.82 | G8: 58.5 | H8: 3 | I8: =IF(D8="Long",(F8-G8)*H8,(G8-F8)*0) -> 27.96 | J8: 2 | K8: =I8*J8 -> 55.92 | L8: Open | M8: =SUMIF(Executions!B:B,A8,Executions!H:H) -> 0
A9: ="T-"& TEXT(ROW()-1,"000") -> T-008 | B9: 46048 | C9: MNST | D9: Long | E9: Trend Continuation | F9: 75.67 | G9: 73.15 | H9: 12 | I9: =IF(D9="Long",(F9-G9)*H9,(G9-F9)*0) -> 30.24 | J9: 2 | K9: =I9*J9 -> 60.48 | L9: Closed | M9: =SUMIF(Executions!B:B,A9,Executions!H:H) -> 80.4
A10: ="T-"& TEXT(ROW()-1,"000") -> T-009 | B10: 46083 | C10: UUUU | D10: Long | E10: Trend Continuation | F10: 22.46 | G10: 19.35 | H10: 7 | I10: =IF(D10="Long",(F10-G10)*H10,(G10-F10)*0) -> 21.77 | J10: 2 | K10: =I10*J10 -> 43.54 | L10: Open | M10: =SUMIF(Executions!B:B,A10,Executions!H:H) -> 0
A11: ="T-"& TEXT(ROW()-1,"000") -> T-010 | B11: 46083 | C11: NRT | D11: Long | E11: Trend Continuation | F11: 8.99 | G11: 8.16 | H11: 27 | I11: =IF(D11="Long",(F11-G11)*H11,(G11-F11)*0) -> 22.41 | J11: 2 | K11: =I11*J11 -> 44.82 | L11: Closed | M11: =SUMIF(Executions!B:B,A11,Executions!H:H) -> 0
A12: ="T-"& TEXT(ROW()-1,"000") -> T-011 | B12: 46084 | C12: TJX | D12: Long | E12: Breakout | F12: 152.17 | G12: 150.48 | H12: 6 | I12: =IF(D12="Long",(F12-G12)*H12,(G12-F12)*0) -> 10.14 | J12: 2 | K12: =I12*J12 -> 20.28 | L12: Closed | M12: =SUMIF(Executions!B:B,A12,Executions!H:H) -> 24.42
A13: ="T-"& TEXT(ROW()-1,"000") -> T-012 | B13: 46085 | C13: APPS | D13: Long | E13: CT Reversal | F13: 4.27 | G13: 3.75 | H13: 42 | I13: =IF(D13="Long",(F13-G13)*H13,(G13-F13)*0) -> 21.84 | J13: 2 | K13: =I13*J13 -> 43.68 | L13: Open | M13: =SUMIF(Executions!B:B,A13,Executions!H:H) -> 0
... A15: ="T-"& TEXT(ROW()-1,"000") -> T-014 | B15: 46079 | C15: LULU | D15: Long | E15: CT Reversal | F15: 177.48 | G15: 166.83 | H15: 2 | I15: =IF(D15="Long",(F15-G15)*H15,(G15-F15)*0) -> 21.3 | J15: 2 | K15: =I15*J15 -> 42.6 | L15: Closed | M15: =SUMIF(Executions!B:B,A15,Executions!H:H) -> -21.72

Sheet Executions
A1: Exec_ID | B1: Trade_ID | C1: Date | D1: Ticker | E1: Action | F1: Execution Price | G1: Shares Closed | H1: P&L | I1: R Contribution
A2: =ROW()-1 -> 1 | B2: T-001 | C2: 46077 | D2: =VLOOKUP(B2,Trades!A$1:M100000,3,FALSE) -> ONDS | E2: Sell | F2: 9.81 | G2: 18 | H2: =IF(VLOOKUP(B2,Trades!A:M,4,FALSE)="Long",(F2-VLOOKUP(B2,Trades!A:M,6,FALSE))*G2,(VLOOKUP(B2,Trades!A:M,6,FALSE)-F2)*G2) -> -23.4 | I2: =H2/Trades!I2 -> -1
A3: =ROW()-1 -> 2 | B3: T-004 | C3: 46077 | D3: =VLOOKUP(B3,Trades!A$1:M100001,3,FALSE) -> NG | E3: Sell | F3: 11.765 | G3: 18 | H3: =IF(VLOOKUP(B3,Trades!A:M,4,FALSE)="Long",(F3-VLOOKUP(B3,Trades!A:M,6,FALSE))*G3,(VLOOKUP(B3,Trades!A:M,6,FALSE)-F3)*G3) -> 25.11 | I3: =H3/Trades!I3 -> 1.1434426
A4: =ROW()-1 -> 3 | B4: T-002 | C4: 46078 | D4: =VLOOKUP(B4,Trades!A$1:M100002,3,FALSE) -> DNN | E4: Sell | F4: 4.29 | G4: 61 | H4: =IF(VLOOKUP(B4,Trades!A:M,4,FALSE)="Long",(F4-VLOOKUP(B4,Trades!A:M,6,FALSE))*G4,(VLOOKUP(B4,Trades!A:M,6,FALSE)-F4)*G4) -> 6.71 | I4: =H4/Trades!I4 -> 0.23153899
A5: =ROW()-1 -> 4 | B5: T-008 | C5: 46083 | D5: =VLOOKUP(B5,Trades!A$1:M100003,3,FALSE) -> MNST | E5: Sell | F5: 82.37 | G5: 12 | H5: =IF(VLOOKUP(B5,Trades!A:M,4,FALSE)="Long",(F5-VLOOKUP(B5,Trades!A:M,6,FALSE))*G5,(VLOOKUP(B5,Trades!A:M,6,FALSE)-F5)*G5) -> 80.4 | I5: =H5/Trades!I5 -> 2.4275362
A6: =ROW()-1 -> 5 | B6: T-004 | C6: 46084 | D6: =VLOOKUP(B6,Trades!A$1:M100004,3,FALSE) -> NG | E6: Sell | F6: 12.27 | G6: 18 | H6: =IF(VLOOKUP(B6,Trades!A:M,4,FALSE)="Long",(F6-VLOOKUP(B6,Trades!A:M,6,FALSE))*G6,(VLOOKUP(B6,Trades!A:M,6,FALSE)-F6)*G6) -> 34.2 | I6: =H6/Trades!I6 -> 1.8
A7: =ROW()-1 -> 6 | B7: T-011 | C7: 46084 | D7: =VLOOKUP(B7,Trades!A$1:M100005,3,FALSE) -> TJX | E7: Sell | F7: 156.24 | G7: 6 | H7: =IF(VLOOKUP(B7,Trades!A:M,4,FALSE)="Long",(F7-VLOOKUP(B7,Trades!A:M,6,FALSE))*G7,(VLOOKUP(B7,Trades!A:M,6,FALSE)-F7)*G7) -> 24.42 | I7: =H7/Trades!I7 -> 1.4908425
A8: =ROW()-1 -> 7 | B8: T-005 | C8: 46085 | D8: =VLOOKUP(B8,Trades!A$1:M100006,3,FALSE) -> ATEC | E8: Sell | F8: 12.832 | G8: 19 | H8: =IF(VLOOKUP(B8,Trades!A:M,4,FALSE)="Long",(F8-VLOOKUP(B8,Trades!A:M,6,FALSE))*G8,(VLOOKUP(B8,Trades!A:M,6,FALSE)-F8)*G8) -> -10.602 | I8: =H8/Trades!I8 -> -0.37918455
A9: =ROW()-1 -> 8 | B9: T-014 | C9: 46087 | D9: LULU | E9: Sell | F9: 166.62 | G9: 2 | H9: =IF(VLOOKUP(B9,Trades!A:M,4,FALSE)="Long",(F9-VLOOKUP(B9,Trades!A:M,6,FALSE))*G9,(VLOOKUP(B9,Trades!A:M,6,FALSE)-F9)*G9) -> -21.72 | I9: =H9/Trades!I9 -> -0.71825397

Sheet Setups
A1: Setup Name | B1: Total Trades | C1: Wins | D1: Losses | E1: Win Rate | F1: Total R | G1: Avg R per Trade | H1: Profit Factor | I1: Expectancy | J1: Status
A2: Breakout | B2: =COUNTIF(Trades!E:E,A2) -> 3 | C2: =COUNTIFS(Trades!E:E, A2,Trades!M:M, ">0") -> 2 | D2: =COUNTIFS(Trades!E:E, A2, Trades!M:M, "<0") -> 0 | E2: =IFERROR(C2/B2,0) -> 0.66666667 | F2: =SUMIF(Trades!E:E,A2,Trades!M:M) -> 83.73 | G2: =IFERROR(F2/B2,0) -> 27.91 | H2: =IFERROR( SUMIFS(Trades!M:M, Trades!E:E, A2, Trades!M:M, ">0")/ABS(SUMIFS(Trades!M:M,Trades!E:E, A2,Trades!M:M,"<0")),0) -> 0 | I2: =IFERROR(F2/B2,0) -> 27.91
A3: Pullback | B3: =COUNTIF(Trades!E:E,A3) -> 0 | C3: =COUNTIFS(Trades!E:E, A3,Trades!M:M, ">0") -> 0 | D3: =COUNTIFS(Trades!E:E, A3, Trades!M:M, "<0") -> 0 | E3: =IFERROR(C3/B3,0) -> 0 | F3: =SUMIF(Trades!E:E,A3,Trades!M:M) -> 0 | G3: =IFERROR(F3/B3,0) -> 0 | H3: =IFERROR( SUMIFS(Trades!M:M, Trades!E:E, A3, Trades!M:M, ">0")/ABS(SUMIFS(Trades!M:M, Trades!E:E, A3, Trades!M:M,"<0")),0) -> 0 | I3: =IFERROR(F3/B3,0) -> 0
A4: Range Break | B4: =COUNTIF(Trades!E:E,A4) -> 0 | C4: =COUNTIFS(Trades!E:E, A4,Trades!M:M, ">0") -> 0 | D4: =COUNTIFS(Trades!E:E, A4, Trades!M:M, "<0") -> 0 | E4: =IFERROR(C4/B4,0) -> 0 | F4: =SUMIF(Trades!E:E,A4,Trades!M:M) -> 0 | G4: =IFERROR(F4/B4,0) -> 0 | H4: =IFERROR( SUMIFS(Trades!M:M, Trades!E:E, A4, Trades!M:M, ">0")/ABS(SUMIFS(Trades!M:M, Trades!E:E, A4, Trades!M:M,"<0")),0) -> 0 | I4: =IFERROR(F4/B4,0) -> 0
A5: Reversal | B5: =COUNTIF(Trades!E:E,A5) -> 1 | C5: =COUNTIFS(Trades!E:E, A5,Trades!M:M, ">0") -> 0 | D5: =COUNTIFS(Trades!E:E, A5, Trades!M:M, "<0") -> 0 | E5: =IFERROR(C5/B5,0) -> 0 | F5: =SUMIF(Trades!E:E,A5,Trades!M:M) -> 0 | G5: =IFERROR(F5/B5,0) -> 0 | H5: =IFERROR( SUMIFS(Trades!M:M, Trades!E:E, A5, Trades!M:M, ">0")/ABS(SUMIFS(Trades!M:M, Trades!E:E, A5, Trades!M:M,"<0")),0) -> 0 | I5: =IFERROR(F5/B5,0) -> 0
A6: Earning Play | B6: =COUNTIF(Trades!E:E,A6) -> 0 | C6: =COUNTIFS(Trades!E:E, A6,Trades!M:M, ">0") -> 0 | D6: =COUNTIFS(Trades!E:E, A6, Trades!M:M, "<0") -> 0 | E6: =IFERROR(C6/B6,0) -> 0 | F6: =SUMIF(Trades!E:E,A6,Trades!M:M) -> 0 | G6: =IFERROR(F6/B6,0) -> 0 | H6: =IFERROR( SUMIFS(Trades!M:M, Trades!E:E, A6, Trades!M:M, ">0")/ABS(SUMIFS(Trades!M:M, Trades!E:E, A6, Trades!M:M,"<0")),0) -> 0 | I6: =IFERROR(F6/B6,0) -> 0
A7: A+ Setup | B7: =COUNTIF(Trades!E:E,A7) -> 0 | C7: =COUNTIFS(Trades!E:E, A7,Trades!M:M, ">0") -> 0 | D7: =COUNTIFS(Trades!E:E, A7, Trades!M:M, "<0") -> 0 | E7: =IFERROR(C7/B7,0) -> 0 | F7: =SUMIF(Trades!E:E,A7,Trades!M:M) -> 0 | G7: =IFERROR(F7/B7,0) -> 0 | H7: =IFERROR( SUMIFS(Trades!M:M, Trades!E:E, A7, Trades!M:M, ">0")/ABS(SUMIFS(Trades!M:M, Trades!E:E, A7, Trades!M:M,"<0")),0) -> 0 | I7: =IFERROR(F7/B7,0) -> 0
A8: Buy the Dip | B8: =COUNTIF(Trades!E:E,A8) -> 0 | C8: =COUNTIFS(Trades!E:E, A8,Trades!M:M, ">0") -> 0 | D8: =COUNTIFS(Trades!E:E, A8, Trades!M:M, "<0") -> 0 | E8: =IFERROR(C8/B8,0) -> 0 | F8: =SUMIF(Trades!E:E,A8,Trades!M:M) -> 0 | G8: =IFERROR(F8/B8,0) -> 0 | H8: =IFERROR( SUMIFS(Trades!M:M, Trades!E:E, A8, Trades!M:M, ">0")/ABS(SUMIFS(Trades!M:M, Trades!E:E, A8, Trades!M:M,"<0")),0) -> 0 | I8: =IFERROR(F8/B8,0) -> 0
A9: Trend Continuation | B9: =COUNTIF(Trades!E:E,A9) -> 5 | C9: =COUNTIFS(Trades!E:E, A9,Trades!M:M, ">0") -> 2 | D9: =COUNTIFS(Trades!E:E, A9, Trades!M:M, "<0") -> 0 | E9: =IFERROR(C9/B9,0) -> 0.4 | F9: =SUMIF(Trades!E:E,A9,Trades!M:M) -> 87.11 | G9: =IFERROR(F9/B9,0) -> 17.422 | H9: =IFERROR( SUMIFS(Trades!M:M, Trades!E:E, A9, Trades!M:M, ">0")/ABS(SUMIFS(Trades!M:M, Trades!E:E, A9, Trades!M:M,"<0")),0) -> 0 | I9: =IFERROR(F9/B9,0) -> 17.422
A10: CT Reversal | B10: =COUNTIF(Trades!E:E,A10) -> 5 | C10: =COUNTIFS(Trades!E:E, A10,Trades!M:M, ">0") -> 0 | D10: =COUNTIFS(Trades!E:E, A10, Trades!M:M, "<0") -> 3 | E10: =IFERROR(C10/B10,0) -> 0 | F10: =SUMIF(Trades!E:E,A10,Trades!M:M) -> -55.722 | G10: =IFERROR(F10/B10,0) -> -11.1444 | H10: =IFERROR( SUMIFS(Trades!M:M, Trades!E:E, A10, Trades!M:M, ">0")/ABS(SUMIFS(Trades!M:M, Trades!E:E, A10, Trades!M:M,"<0")),0) -> 0 | I10: =IFERROR(F10/B10,0) -> -11.1444
A11: Other | B11: =COUNTIF(Trades!E:E,A11) -> 0 | C11: =COUNTIFS(Trades!E:E, A11,Trades!M:M, ">0") -> 0 | D11: =COUNTIFS(Trades!E:E, A11, Trades!M:M, "<0") -> 0 | E11: =IFERROR(C11/B11,0) -> 0 | F11: =SUMIF(Trades!E:E,A11,Trades!M:M) -> 0 | G11: =IFERROR(F11/B11,0) -> 0 | H11: =IFERROR( SUMIFS(Trades!M:M, Trades!E:E, A11, Trades!M:M, ">0")/ABS(SUMIFS(Trades!M:M, Trades!E:E, A11, Trades!M:M,"<0")),0) -> 0 | I11: =IFERROR(F11/B11,0) -> 0

Sheet Mistakes
A1: Trade_ID | B1: Date | C1: Mistake_Type | D1: Preventable | E1: Cost in R | F1: Notes
A2: T-001 | B2: 46077 | C2: Technical | D2: No | E2: -1 | F2: MACD never got confirmation after a try for continuation
A3: T-002 | B3: 46078 | C3: Technical | D3: Yes | E3: 0 | F3: It was closed with earnings, but the entry was timed because I didn't consider earnings release

Sheet Daily Journal
A1: Date | B1: Starting Balance | C1: Ending Equity | D1: Daily R | E1: Emotions | F1: Disciplince Score | G1: Market Contition | H1: Lessons | I1: Sleep Quality | J1: Focus Level
A2: 46077 | B2: 9076 | C2: 9117 | D2: =C2-B2 -> 41 | E2: Calm, reduce portfolio, but difficulty to find entries | F2: 4/5 | G2: Most indexes are green, VIX open above 20, but it dropped to 19, still high | H2: I sceened for entries all they long, but there is few A+ options, the market shows a lot of volatility | I2: Good | J2: High
A3: 46078 | B3: 9117 | C3: 9113 | D3: =C3-B3 -> -4 | E3: The stocks picked are holding the volatility, butit didn't grow | F3: 4/5 | G3: The indexes are gren again, VIX is around 18 levels | H3: It is important to consider earnings release before opening positions, today it was a couple of risky entry that luckily worked out | I3: Good | J3: Medium
A4: 46079 | B4: 9113 | C4: 9171 | D4: =C4-B4 -> 58 | E4: Several entries with .25 risk per trade, they seem to be in good momentum since I am trying to enter after bouncing | F4: 5/5 | G4: The market started green, but the earnings released by NVDA added more uncertainty about the AI and it has increased the volatility, VIX has gone over 20 again and the market is falling in general | H4: Patience for entries are everything | I4: Good | J4: High
A5: 46080 | B5: 9171 | C5: 9186 | D5: =C5-B5 -> 15 | E5: Despite the market falling, most of the stocks selected are showing strength I bought them from a relative slow aiming to a counter trend reversal or reversal, for the moment most of the stocks are working which leaves me at easy. Is pretty likely that the portfolio will drop during the day. At the end I manage to do a marginal increase of 15 bucks | F5: 46147 | G5: Most of the market opened with a gap down, and it is mostly falling, VIX is over 20 again but this time there is no a clear trigger, most likely is related with AI concerns that have been increasing the volatility in recent | H5: Look for entries in the structure, not the price, it is what is working. | I5: Good | J5: Low

Sheet Dashboard
A1: Core Stats
A2: Total Trades: | B2: =COUNTA(Trades!A:A)-1 -> 14
A3: Win Rate: | B3: =COUNTIF(Trades!M:M,">0")/COUNT(Trades!M:M) -> 0.28571429
A4: Avg R: | B4: =AVERAGE(Trades!M:M) -> 8.2227143
A5: Total R: | B5: =SUM(Trades!M:M) -> 115.118
A6: Profit Factor | B6: =SUMIF(Trades!M:M,">0")/ABS(SUM(Trades!M:M,""<0)) -> 1.4840425
A8: Risk Metrics
A9: Max Win: | B9: =MAX(Trades!M:M) -> 80.4
A10: Max Loss: | B10: =MIN(Trades!M:M) -> -23.4
A11: Avg Win: | B11: =AVERAGEIF(Trades!M:M,">0") -> 42.71
A12: Avg Loss: | B12: =AVERAGEIF(Trades!M:M,"<0") -> -18.574
